setup.py
ModelBuild/__init__.py
ModelBuild/coefficients.py
ModelPrediction/__init__.py
ModelPrediction/arpu_functions.py
ModelPrediction/churn_functions.py
ModelPrediction/data_functions.py
Optimisation.egg-info/PKG-INFO
Optimisation.egg-info/SOURCES.txt
Optimisation.egg-info/dependency_links.txt
Optimisation.egg-info/requires.txt
Optimisation.egg-info/top_level.txt